{
    "$id": "https://ns.adobe.com/prudential/mixins/1c25adf844fb44be9636379a6ced37212693002bf26eed3b",
    "meta:altId": "_prudential.mixins.1c25adf844fb44be9636379a6ced37212693002bf26eed3b",
    "meta:resourceType": "mixins",
    "version": "1.1",
    "title": "EDP Account Identity",
    "type": "object",
    "description": "",
    "definitions": {
        "customFields": {
            "properties": {
                "_prudential": {
                    "type": "object",
                    "properties": {
                        "accountId": {
                            "required": [],
                            "type": "string",
                            "title": "Account Id",
                            "meta:xdmType": "string",
                            "description": "Customer Account # / Policy #\n"
                        }
                    },
                    "meta:xdmType": "object"
                }
            }
        }
    },
    "allOf": [
        {
            "$ref": "#/definitions/customFields",
            "type": "object",
            "meta:xdmType": "object"
        }
    ],
    "imsOrg": "A3F5A8DC5886052D0A495CC3@AdobeOrg",
    "meta:extensible": true,
    "meta:abstract": true,
    "meta:intendedToExtend": [
        "https://ns.adobe.com/xdm/context/profile"
    ],
    "meta:xdmType": "object",
    "meta:registryMetadata": {
        "repo:createdDate": 1668496417049,
        "repo:lastModifiedDate": 1668510686018,
        "xdm:createdClientId": "84f33f69f3fb4e5892cf05e503891de9",
        "xdm:lastModifiedClientId": "acp_xql_gateway",
        "xdm:createdUserId": "8D40475162A085200A495FB7@techacct.adobe.com",
        "xdm:lastModifiedUserId": "E193342C630F91B20A495C0A@58f520ae5b81c35b0a495d34",
        "eTag": "cd72e6bed0483f622d9b58cfe8c232571ec85fc25ba2ee82e4aa2cddd07e904d",
        "meta:globalLibVersion": "1.38.2"
    },
    "meta:containerId": "87ae5ec3-c2a2-4372-ae5e-c3c2a233724d",
    "meta:sandboxId": "87ae5ec3-c2a2-4372-ae5e-c3c2a233724d",
    "meta:sandboxType": "development",
    "meta:tenantNamespace": "_prudential",
    "meta:allFieldAccess": true
}