{
    "$id": "https://ns.adobe.com/prudential/mixins/29ee3bb68f725e02998489087167e06929287c2f826e7e1c",
    "meta:altId": "_prudential.mixins.29ee3bb68f725e02998489087167e06929287c2f826e7e1c",
    "meta:resourceType": "mixins",
    "version": "1.0",
    "title": "EDP Party Identity",
    "type": "object",
    "description": "Defines identity field to uniquely identify the Party",
    "definitions": {
        "customFields": {
            "properties": {
                "_prudential": {
                    "type": "object",
                    "properties": {
                        "partyId": {
                            "required": [],
                            "type": "string",
                            "description": "Id column to uniquely identify the party",
                            "title": "Party Id",
                            "meta:xdmType": "string"
                        }
                    },
                    "meta:xdmType": "object"
                }
            }
        }
    },
    "allOf": [
        {
            "$ref": "#/definitions/customFields",
            "type": "object",
            "meta:xdmType": "object"
        }
    ],
    "imsOrg": "A3F5A8DC5886052D0A495CC3@AdobeOrg",
    "meta:extensible": true,
    "meta:abstract": true,
    "meta:intendedToExtend": [
        "https://ns.adobe.com/xdm/context/profile"
    ],
    "meta:xdmType": "object",
    "meta:registryMetadata": {
        "repo:createdDate": 1667893420654,
        "repo:lastModifiedDate": 1667893420654,
        "xdm:createdClientId": "84f33f69f3fb4e5892cf05e503891de9",
        "xdm:lastModifiedClientId": "84f33f69f3fb4e5892cf05e503891de9",
        "xdm:createdUserId": "8D40475162A085200A495FB7@techacct.adobe.com",
        "xdm:lastModifiedUserId": "8D40475162A085200A495FB7@techacct.adobe.com",
        "eTag": "ae37f280ac6cae6303f7b2b5ee27d2380125bd2d48f7a4dac05f18051b4a2c66",
        "meta:globalLibVersion": "1.38.2"
    },
    "meta:containerId": "b7ba0b0f-2458-4ab2-ba0b-0f2458dab27b",
    "meta:sandboxId": "b7ba0b0f-2458-4ab2-ba0b-0f2458dab27b",
    "meta:sandboxType": "development",
    "meta:tenantNamespace": "_prudential",
    "meta:allFieldAccess": true
}