{
    "$id": "https://ns.adobe.com/deloitte_digitalengage/mixins/2ed0a9c0a43ce3b8d704c1d458d21d653d937b5784934cc4",
    "meta:altId": "_deloitte_digitalengage.mixins.2ed0a9c0a43ce3b8d704c1d458d21d653d937b5784934cc4",
    "meta:resourceType": "mixins",
    "version": "1.0",
    "title": "Macys DaaS Details",
    "type": "object",
    "description": "",
    "definitions": {
        "customFields": {
            "properties": {
                "_deloitte_digitalengage": {
                    "type": "object",
                    "properties": {
                        "daasDetails": {
                            "properties": {
                                "daasUpdTs": {
                                    "required": [],
                                    "format": "date-time",
                                    "type": "string",
                                    "description": "",
                                    "title": "Daas record update timestamp",
                                    "meta:xdmType": "date-time"
                                },
                                "daasCrtTs": {
                                    "required": [],
                                    "format": "date-time",
                                    "type": "string",
                                    "description": "",
                                    "title": "Daas record create timestamp",
                                    "meta:xdmType": "date-time"
                                },
                                "daasStatCd": {
                                    "required": [],
                                    "type": "string",
                                    "description": "",
                                    "title": "Daas Status Code",
                                    "meta:xdmType": "string"
                                },
                                "daasJobName": {
                                    "required": [],
                                    "type": "string",
                                    "description": "",
                                    "title": "Daas Job Name",
                                    "meta:xdmType": "string"
                                },
                                "dassLoadID": {
                                    "required": [],
                                    "type": "string",
                                    "description": "",
                                    "title": "Daas load id",
                                    "meta:xdmType": "string"
                                },
                                "daasUserId": {
                                    "required": [],
                                    "type": "string",
                                    "description": "",
                                    "title": "Daas User Id",
                                    "meta:xdmType": "string"
                                },
                                "daasSrcDelInd": {
                                    "required": [],
                                    "type": "string",
                                    "title": "DaaS Source Delete Indicator",
                                    "meta:xdmType": "string"
                                }
                            },
                            "required": [],
                            "type": "object",
                            "title": "DaaS Details",
                            "meta:xdmType": "object"
                        }
                    },
                    "meta:xdmType": "object"
                }
            }
        }
    },
    "allOf": [
        {
            "$ref": "#/definitions/customFields",
            "type": "object",
            "meta:xdmType": "object"
        }
    ],
    "imsOrg": "8D0867C25245AE650A490D4C@AdobeOrg",
    "meta:extensible": true,
    "meta:abstract": true,
    "meta:intendedToExtend": [
        "https://ns.adobe.com/deloitte_digitalengage/classes/dfc9a031d10d9add185f5cc6a177502e7734aeff6d361fb9"
    ],
    "meta:xdmType": "object",
    "meta:registryMetadata": {
        "repo:createdDate": 1659509297057,
        "repo:lastModifiedDate": 1659509297057,
        "xdm:createdClientId": "c916220f349947bf94161cd8cb74b4a8",
        "xdm:lastModifiedClientId": "c916220f349947bf94161cd8cb74b4a8",
        "xdm:createdUserId": "A38347AE62EA0A350A495FA0@techacct.adobe.com",
        "xdm:lastModifiedUserId": "A38347AE62EA0A350A495FA0@techacct.adobe.com",
        "eTag": "9ea7e02f52ddff892151888b9ff0ebe50b58472503e0f3cb6f28bbb160dbf8fc",
        "meta:globalLibVersion": "1.39.1.1"
    },
    "meta:containerId": "tenant",
    "meta:sandboxId": "e0db4d28-ca91-4847-9b4d-28ca91184709",
    "meta:sandboxType": "production",
    "meta:tenantNamespace": "_deloitte_digitalengage",
    "meta:allFieldAccess": true
}